meta_ai_api_tool_call/__init__.py
meta_ai_api_tool_call/main.py
meta_ai_api_tool_call-0.1.3.dist-info/METADATA
meta_ai_api_tool_call-0.1.3.dist-info/WHEEL
meta_ai_api_tool_call-0.1.3.dist-info/top_level.txt
meta_ai_api_tool_call-0.1.3.dist-info/RECORD
