Metadata-Version: 2.4
Name: meta_ai_api_tool_call
Version: 0.1.3
Summary: A Python package for interacting with Meta AI API (reverse engineered) with tool calls.
Home-page: https://github.com/mr-destructive/meta_ai_api_tool_call
Author: Meet Gor
Author-email: gormeet711@gmail.com
Project-URL: Source, https://github.com/mr-destructive/meta_ai_api_tool_call
Project-URL: Tracker, https://github.com/mr-destructive/meta_ai_api_tool_call/issues
Classifier: Programming Language :: Python :: 3
Classifier: License :: OSI Approved :: MIT License
Classifier: Operating System :: OS Independent
Classifier: Intended Audience :: Developers
Classifier: Development Status :: 3 - Alpha
Classifier: Topic :: Software Development :: Libraries :: Python Modules
Requires-Python: >=3.7
Requires-Dist: requests-html
Requires-Dist: beautifulsoup4
Requires-Dist: requests
Requires-Dist: lxml
Requires-Dist: lxml_html_clean
Dynamic: author
Dynamic: author-email
Dynamic: classifier
Dynamic: description
Dynamic: description-content-type
Dynamic: home-page
Dynamic: project-url
Dynamic: requires-dist
Dynamic: requires-python
Dynamic: summary
